{
  "openapi": "3.0.3",
  "info": {
    "title": "faclab-invoicing",
    "version": "1.0.0",
    "description": "Faclab Invoicing API"
  },
  "components": {
    "schemas": {}
  },
  "paths": {
    "/health": {
      "get": {
        "responses": {
          "200": {
            "description": "Default Response",
            "content": {
              "application/json": {
                "schema": {
                  "type": "object",
                  "properties": {
                    "status": {
                      "type": "string"
                    }
                  }
                }
              }
            }
          }
        }
      }
    },
    "/api/certificates": {
      "post": {
        "summary": "Upload a .p12 digital signature certificate",
        "tags": [
          "Certificates"
        ],
        "description": "Accepts a PKCS#12 (.p12) file and its password. The service parses the certificate metadata, stores the file in S3, and persists the metadata in DynamoDB. The returned `id` should be saved as the `signingCertId` field in the company configuration (PUT /api/company-config) so the service uses this certificate to sign invoices.",
        "requestBody": {
          "required": true,
          "content": {
            "multipart/form-data": {
              "schema": {
                "type": "object",
                "required": [
                  "file",
                  "password"
                ],
                "properties": {
                  "file": {
                    "type": "string",
                    "format": "binary",
                    "description": "PKCS#12 (.p12) certificate file issued by a trusted CA (e.g. BCE, Security Data, ANF)."
                  },
                  "password": {
                    "type": "string",
                    "description": "Password that protects the .p12 file. Required to extract the private key."
                  }
                }
              }
            }
          }
        },
        "responses": {
          "201": {
            "description": "Certificate uploaded and parsed successfully.",
            "content": {
              "application/json": {
                "schema": {
                  "type": "object",
                  "properties": {
                    "data": {
                      "type": "object",
                      "properties": {
                        "id": {
                          "type": "string",
                          "format": "uuid",
                          "description": "Unique certificate identifier. Set this value as the `signingCertId` in the company configuration (PUT /api/company-config)."
                        },
                        "serialNumber": {
                          "type": "string",
                          "description": "Serial number extracted from the X.509 certificate inside the .p12 file."
                        },
                        "subject": {
                          "type": "string",
                          "description": "Distinguished Name (DN) of the certificate subject in RFC 4514 format.",
                          "example": "CN=JUAN PEREZ, O=BCE, C=EC"
                        },
                        "issuer": {
                          "type": "string",
                          "description": "Distinguished Name (DN) of the Certificate Authority that issued this certificate.",
                          "example": "CN=BCE ENTIDAD CERTIFICADORA, O=BCE, C=EC"
                        },
                        "validFrom": {
                          "type": "string",
                          "format": "date-time",
                          "description": "Certificate validity start date (ISO 8601)."
                        },
                        "validTo": {
                          "type": "string",
                          "format": "date-time",
                          "description": "Certificate expiry date (ISO 8601). Invoices cannot be signed after this date."
                        },
                        "fileName": {
                          "type": "string",
                          "description": "Original filename of the uploaded .p12 file.",
                          "example": "firma_electronica.p12"
                        },
                        "s3Url": {
                          "type": "string",
                          "format": "uri",
                          "description": "S3 URL where the certificate file is stored."
                        },
                        "uploadedAt": {
                          "type": "string",
                          "format": "date-time",
                          "description": "Timestamp when the certificate was uploaded (ISO 8601)."
                        }
                      }
                    },
                    "meta": {
                      "type": "object",
                      "properties": {
                        "requestId": {
                          "type": "string"
                        },
                        "timestamp": {
                          "type": "string",
                          "format": "date-time"
                        }
                      },
                      "required": [
                        "requestId",
                        "timestamp"
                      ]
                    }
                  },
                  "required": [
                    "data",
                    "meta"
                  ],
                  "description": "Certificate uploaded and parsed successfully."
                }
              }
            }
          },
          "400": {
            "description": "Missing file, wrong file extension, or invalid request.",
            "content": {
              "application/json": {
                "schema": {
                  "type": "object",
                  "properties": {
                    "errors": {
                      "type": "array",
                      "items": {
                        "type": "object",
                        "properties": {
                          "code": {
                            "type": "string"
                          },
                          "message": {
                            "type": "string"
                          }
                        },
                        "required": [
                          "code",
                          "message"
                        ]
                      }
                    },
                    "meta": {
                      "type": "object",
                      "properties": {
                        "requestId": {
                          "type": "string"
                        },
                        "timestamp": {
                          "type": "string",
                          "format": "date-time"
                        }
                      },
                      "required": [
                        "requestId",
                        "timestamp"
                      ]
                    }
                  },
                  "required": [
                    "errors",
                    "meta"
                  ],
                  "description": "Missing file, wrong file extension, or invalid request."
                }
              }
            }
          },
          "422": {
            "description": "File could not be parsed — wrong password or corrupted .p12.",
            "content": {
              "application/json": {
                "schema": {
                  "type": "object",
                  "properties": {
                    "errors": {
                      "type": "array",
                      "items": {
                        "type": "object",
                        "properties": {
                          "code": {
                            "type": "string"
                          },
                          "message": {
                            "type": "string"
                          }
                        },
                        "required": [
                          "code",
                          "message"
                        ]
                      }
                    },
                    "meta": {
                      "type": "object",
                      "properties": {
                        "requestId": {
                          "type": "string"
                        },
                        "timestamp": {
                          "type": "string",
                          "format": "date-time"
                        }
                      },
                      "required": [
                        "requestId",
                        "timestamp"
                      ]
                    }
                  },
                  "required": [
                    "errors",
                    "meta"
                  ],
                  "description": "File could not be parsed — wrong password or corrupted .p12."
                }
              }
            }
          }
        }
      },
      "get": {
        "summary": "List all certificates",
        "tags": [
          "Certificates"
        ],
        "description": "Returns all certificates stored in the system.",
        "responses": {
          "200": {
            "description": "Default Response",
            "content": {
              "application/json": {
                "schema": {
                  "type": "object",
                  "properties": {
                    "data": {
                      "type": "array",
                      "items": {
                        "type": "object",
                        "properties": {
                          "id": {
                            "type": "string",
                            "format": "uuid",
                            "description": "Unique certificate identifier. Set this value as the `signingCertId` in the company configuration (PUT /api/company-config)."
                          },
                          "serialNumber": {
                            "type": "string",
                            "description": "Serial number extracted from the X.509 certificate inside the .p12 file."
                          },
                          "subject": {
                            "type": "string",
                            "description": "Distinguished Name (DN) of the certificate subject in RFC 4514 format.",
                            "example": "CN=JUAN PEREZ, O=BCE, C=EC"
                          },
                          "issuer": {
                            "type": "string",
                            "description": "Distinguished Name (DN) of the Certificate Authority that issued this certificate.",
                            "example": "CN=BCE ENTIDAD CERTIFICADORA, O=BCE, C=EC"
                          },
                          "validFrom": {
                            "type": "string",
                            "format": "date-time",
                            "description": "Certificate validity start date (ISO 8601)."
                          },
                          "validTo": {
                            "type": "string",
                            "format": "date-time",
                            "description": "Certificate expiry date (ISO 8601). Invoices cannot be signed after this date."
                          },
                          "fileName": {
                            "type": "string",
                            "description": "Original filename of the uploaded .p12 file.",
                            "example": "firma_electronica.p12"
                          },
                          "s3Url": {
                            "type": "string",
                            "format": "uri",
                            "description": "S3 URL where the certificate file is stored."
                          },
                          "uploadedAt": {
                            "type": "string",
                            "format": "date-time",
                            "description": "Timestamp when the certificate was uploaded (ISO 8601)."
                          }
                        }
                      }
                    },
                    "meta": {
                      "type": "object",
                      "properties": {
                        "requestId": {
                          "type": "string"
                        },
                        "timestamp": {
                          "type": "string",
                          "format": "date-time"
                        }
                      },
                      "required": [
                        "requestId",
                        "timestamp"
                      ]
                    }
                  },
                  "required": [
                    "data",
                    "meta"
                  ]
                }
              }
            }
          }
        }
      }
    },
    "/api/certificates/{id}": {
      "get": {
        "summary": "Get a certificate by ID",
        "tags": [
          "Certificates"
        ],
        "description": "Returns the metadata for a single certificate.",
        "parameters": [
          {
            "schema": {
              "type": "string",
              "format": "uuid"
            },
            "in": "path",
            "name": "id",
            "required": true,
            "description": "Certificate UUID."
          }
        ],
        "responses": {
          "200": {
            "description": "Default Response",
            "content": {
              "application/json": {
                "schema": {
                  "type": "object",
                  "properties": {
                    "data": {
                      "type": "object",
                      "properties": {
                        "id": {
                          "type": "string",
                          "format": "uuid",
                          "description": "Unique certificate identifier. Set this value as the `signingCertId` in the company configuration (PUT /api/company-config)."
                        },
                        "serialNumber": {
                          "type": "string",
                          "description": "Serial number extracted from the X.509 certificate inside the .p12 file."
                        },
                        "subject": {
                          "type": "string",
                          "description": "Distinguished Name (DN) of the certificate subject in RFC 4514 format.",
                          "example": "CN=JUAN PEREZ, O=BCE, C=EC"
                        },
                        "issuer": {
                          "type": "string",
                          "description": "Distinguished Name (DN) of the Certificate Authority that issued this certificate.",
                          "example": "CN=BCE ENTIDAD CERTIFICADORA, O=BCE, C=EC"
                        },
                        "validFrom": {
                          "type": "string",
                          "format": "date-time",
                          "description": "Certificate validity start date (ISO 8601)."
                        },
                        "validTo": {
                          "type": "string",
                          "format": "date-time",
                          "description": "Certificate expiry date (ISO 8601). Invoices cannot be signed after this date."
                        },
                        "fileName": {
                          "type": "string",
                          "description": "Original filename of the uploaded .p12 file.",
                          "example": "firma_electronica.p12"
                        },
                        "s3Url": {
                          "type": "string",
                          "format": "uri",
                          "description": "S3 URL where the certificate file is stored."
                        },
                        "uploadedAt": {
                          "type": "string",
                          "format": "date-time",
                          "description": "Timestamp when the certificate was uploaded (ISO 8601)."
                        }
                      }
                    },
                    "meta": {
                      "type": "object",
                      "properties": {
                        "requestId": {
                          "type": "string"
                        },
                        "timestamp": {
                          "type": "string",
                          "format": "date-time"
                        }
                      },
                      "required": [
                        "requestId",
                        "timestamp"
                      ]
                    }
                  },
                  "required": [
                    "data",
                    "meta"
                  ]
                }
              }
            }
          },
          "404": {
            "description": "No certificate found with the given ID.",
            "content": {
              "application/json": {
                "schema": {
                  "type": "object",
                  "properties": {
                    "errors": {
                      "type": "array",
                      "items": {
                        "type": "object",
                        "properties": {
                          "code": {
                            "type": "string"
                          },
                          "message": {
                            "type": "string"
                          }
                        },
                        "required": [
                          "code",
                          "message"
                        ]
                      }
                    },
                    "meta": {
                      "type": "object",
                      "properties": {
                        "requestId": {
                          "type": "string"
                        },
                        "timestamp": {
                          "type": "string",
                          "format": "date-time"
                        }
                      },
                      "required": [
                        "requestId",
                        "timestamp"
                      ]
                    }
                  },
                  "required": [
                    "errors",
                    "meta"
                  ],
                  "description": "No certificate found with the given ID."
                }
              }
            }
          }
        }
      },
      "delete": {
        "summary": "Delete a certificate",
        "tags": [
          "Certificates"
        ],
        "description": "Deletes the certificate from both DynamoDB and S3. If this certificate is currently set as the `signingCertId` in company configuration, invoice signing will fail until a new certificate is configured.",
        "parameters": [
          {
            "schema": {
              "type": "string",
              "format": "uuid"
            },
            "in": "path",
            "name": "id",
            "required": true,
            "description": "Certificate UUID."
          }
        ],
        "responses": {
          "204": {
            "description": "Certificate deleted successfully."
          },
          "404": {
            "description": "No certificate found with the given ID.",
            "content": {
              "application/json": {
                "schema": {
                  "type": "object",
                  "properties": {
                    "errors": {
                      "type": "array",
                      "items": {
                        "type": "object",
                        "properties": {
                          "code": {
                            "type": "string"
                          },
                          "message": {
                            "type": "string"
                          }
                        },
                        "required": [
                          "code",
                          "message"
                        ]
                      }
                    },
                    "meta": {
                      "type": "object",
                      "properties": {
                        "requestId": {
                          "type": "string"
                        },
                        "timestamp": {
                          "type": "string",
                          "format": "date-time"
                        }
                      },
                      "required": [
                        "requestId",
                        "timestamp"
                      ]
                    }
                  },
                  "required": [
                    "errors",
                    "meta"
                  ],
                  "description": "No certificate found with the given ID."
                }
              }
            }
          }
        }
      }
    },
    "/api/company-config": {
      "put": {
        "summary": "Create or update the company fiscal configuration",
        "tags": [
          "Company Config"
        ],
        "description": "Upserts the singleton company configuration used when generating invoices. This must be configured before the service can process any `sales.confirmed` Kafka events. The `invoiceSequence` field is optional — if omitted, the current counter is preserved.",
        "requestBody": {
          "required": true,
          "content": {
            "application/json": {
              "schema": {
                "type": "object",
                "required": [
                  "taxId",
                  "name",
                  "tradeName",
                  "mainAddress",
                  "branchAddress",
                  "branchCode",
                  "salePointCode",
                  "environment",
                  "emissionType"
                ],
                "properties": {
                  "taxId": {
                    "type": "string",
                    "minLength": 13,
                    "maxLength": 13,
                    "description": "Company RUC — exactly 13 digits."
                  },
                  "name": {
                    "type": "string",
                    "maxLength": 64,
                    "description": "Legal company name (max 64 chars)."
                  },
                  "tradeName": {
                    "type": "string",
                    "maxLength": 64,
                    "description": "Trade name (max 64 chars)."
                  },
                  "mainAddress": {
                    "type": "string",
                    "description": "Main establishment address."
                  },
                  "branchAddress": {
                    "type": "string",
                    "description": "Branch address printed on invoices."
                  },
                  "branchCode": {
                    "type": "string",
                    "maxLength": 4,
                    "description": "Branch code (max 4 chars)."
                  },
                  "salePointCode": {
                    "type": "string",
                    "maxLength": 4,
                    "description": "Point-of-sale code (max 4 chars)."
                  },
                  "specialTaxpayerResolution": {
                    "type": "string",
                    "maxLength": 32,
                    "description": "SRI special taxpayer resolution number (optional)."
                  },
                  "withholdingAgentResolution": {
                    "type": "string",
                    "maxLength": 32,
                    "description": "SRI withholding agent resolution number (optional)."
                  },
                  "accountingRequired": {
                    "type": "boolean",
                    "description": "Whether the company is obligated to keep accounting records."
                  },
                  "environment": {
                    "type": "number",
                    "enum": [
                      1,
                      2
                    ],
                    "description": "`1` = Testing, `2` = Production."
                  },
                  "emissionType": {
                    "type": "number",
                    "enum": [
                      1
                    ],
                    "description": "`1` = Normal. Only supported value."
                  },
                  "invoiceSequence": {
                    "type": "number",
                    "minimum": 1,
                    "description": "Seed value for the invoice sequence counter. Optional — preserves the existing counter if omitted."
                  },
                  "signingCertId": {
                    "type": "string",
                    "format": "uuid",
                    "description": "UUID of the signing certificate. Use the `id` returned by POST /api/certificates/upload."
                  }
                }
              }
            }
          }
        },
        "responses": {
          "200": {
            "description": "Configuration saved successfully.",
            "content": {
              "application/json": {
                "schema": {
                  "type": "object",
                  "properties": {
                    "data": {
                      "type": "object",
                      "properties": {
                        "taxId": {
                          "type": "string",
                          "description": "Company RUC (13-digit Ecuadorian tax ID).",
                          "example": "1792141001001"
                        },
                        "name": {
                          "type": "string",
                          "description": "Legal company name as registered with the SRI.",
                          "example": "ACME SOLUTIONS S.A."
                        },
                        "tradeName": {
                          "type": "string",
                          "description": "Commercial or trade name shown on invoices.",
                          "example": "ACME"
                        },
                        "mainAddress": {
                          "type": "string",
                          "description": "Main establishment address registered with the SRI."
                        },
                        "branchAddress": {
                          "type": "string",
                          "description": "Branch address printed on invoices."
                        },
                        "branchCode": {
                          "type": "string",
                          "description": "Branch code used in invoice numbering (001–999).",
                          "example": "001"
                        },
                        "salePointCode": {
                          "type": "string",
                          "description": "Point-of-sale code used in invoice numbering (001–999).",
                          "example": "001"
                        },
                        "specialTaxpayerResolution": {
                          "type": [
                            "null",
                            "string"
                          ],
                          "description": "SRI resolution number if the company is a special taxpayer. Null otherwise."
                        },
                        "withholdingAgentResolution": {
                          "type": [
                            "null",
                            "string"
                          ],
                          "description": "SRI resolution number if the company is a withholding agent. Null otherwise."
                        },
                        "accountingRequired": {
                          "type": "boolean",
                          "description": "Whether the company is required to keep accounting records (obligado a llevar contabilidad)."
                        },
                        "environment": {
                          "type": "number",
                          "enum": [
                            1,
                            2
                          ],
                          "description": "SRI environment. `1` = Testing (pruebas), `2` = Production (producción).",
                          "example": 1
                        },
                        "emissionType": {
                          "type": "number",
                          "enum": [
                            1
                          ],
                          "description": "Emission type. `1` = Normal (currently the only supported value).",
                          "example": 1
                        },
                        "invoiceSequence": {
                          "type": "number",
                          "description": "Current sequential invoice counter. Auto-incremented on each invoice creation. Can be seeded on first setup.",
                          "example": 42
                        },
                        "signingCertId": {
                          "type": [
                            "null",
                            "string"
                          ],
                          "format": "uuid",
                          "description": "UUID of the PKCS#12 certificate used to sign invoices. Set this to the `id` returned by the certificate upload endpoint. Null if no certificate has been configured."
                        },
                        "updatedAt": {
                          "type": "string",
                          "format": "date-time",
                          "description": "Timestamp of the last configuration update (ISO 8601)."
                        }
                      }
                    },
                    "meta": {
                      "type": "object",
                      "properties": {
                        "requestId": {
                          "type": "string"
                        },
                        "timestamp": {
                          "type": "string",
                          "format": "date-time"
                        }
                      },
                      "required": [
                        "requestId",
                        "timestamp"
                      ]
                    }
                  },
                  "required": [
                    "data",
                    "meta"
                  ],
                  "description": "Configuration saved successfully."
                }
              }
            }
          },
          "400": {
            "description": "Validation error or missing required fields.",
            "content": {
              "application/json": {
                "schema": {
                  "type": "object",
                  "properties": {
                    "errors": {
                      "type": "array",
                      "items": {
                        "type": "object",
                        "properties": {
                          "code": {
                            "type": "string"
                          },
                          "message": {
                            "type": "string"
                          }
                        },
                        "required": [
                          "code",
                          "message"
                        ]
                      }
                    },
                    "meta": {
                      "type": "object",
                      "properties": {
                        "requestId": {
                          "type": "string"
                        },
                        "timestamp": {
                          "type": "string",
                          "format": "date-time"
                        }
                      },
                      "required": [
                        "requestId",
                        "timestamp"
                      ]
                    }
                  },
                  "required": [
                    "errors",
                    "meta"
                  ],
                  "description": "Validation error or missing required fields."
                }
              }
            }
          }
        }
      },
      "get": {
        "summary": "Get the company fiscal configuration",
        "tags": [
          "Company Config"
        ],
        "description": "Returns the current singleton company configuration.",
        "responses": {
          "200": {
            "description": "Default Response",
            "content": {
              "application/json": {
                "schema": {
                  "type": "object",
                  "properties": {
                    "data": {
                      "type": "object",
                      "properties": {
                        "taxId": {
                          "type": "string",
                          "description": "Company RUC (13-digit Ecuadorian tax ID).",
                          "example": "1792141001001"
                        },
                        "name": {
                          "type": "string",
                          "description": "Legal company name as registered with the SRI.",
                          "example": "ACME SOLUTIONS S.A."
                        },
                        "tradeName": {
                          "type": "string",
                          "description": "Commercial or trade name shown on invoices.",
                          "example": "ACME"
                        },
                        "mainAddress": {
                          "type": "string",
                          "description": "Main establishment address registered with the SRI."
                        },
                        "branchAddress": {
                          "type": "string",
                          "description": "Branch address printed on invoices."
                        },
                        "branchCode": {
                          "type": "string",
                          "description": "Branch code used in invoice numbering (001–999).",
                          "example": "001"
                        },
                        "salePointCode": {
                          "type": "string",
                          "description": "Point-of-sale code used in invoice numbering (001–999).",
                          "example": "001"
                        },
                        "specialTaxpayerResolution": {
                          "type": [
                            "null",
                            "string"
                          ],
                          "description": "SRI resolution number if the company is a special taxpayer. Null otherwise."
                        },
                        "withholdingAgentResolution": {
                          "type": [
                            "null",
                            "string"
                          ],
                          "description": "SRI resolution number if the company is a withholding agent. Null otherwise."
                        },
                        "accountingRequired": {
                          "type": "boolean",
                          "description": "Whether the company is required to keep accounting records (obligado a llevar contabilidad)."
                        },
                        "environment": {
                          "type": "number",
                          "enum": [
                            1,
                            2
                          ],
                          "description": "SRI environment. `1` = Testing (pruebas), `2` = Production (producción).",
                          "example": 1
                        },
                        "emissionType": {
                          "type": "number",
                          "enum": [
                            1
                          ],
                          "description": "Emission type. `1` = Normal (currently the only supported value).",
                          "example": 1
                        },
                        "invoiceSequence": {
                          "type": "number",
                          "description": "Current sequential invoice counter. Auto-incremented on each invoice creation. Can be seeded on first setup.",
                          "example": 42
                        },
                        "signingCertId": {
                          "type": [
                            "null",
                            "string"
                          ],
                          "format": "uuid",
                          "description": "UUID of the PKCS#12 certificate used to sign invoices. Set this to the `id` returned by the certificate upload endpoint. Null if no certificate has been configured."
                        },
                        "updatedAt": {
                          "type": "string",
                          "format": "date-time",
                          "description": "Timestamp of the last configuration update (ISO 8601)."
                        }
                      }
                    },
                    "meta": {
                      "type": "object",
                      "properties": {
                        "requestId": {
                          "type": "string"
                        },
                        "timestamp": {
                          "type": "string",
                          "format": "date-time"
                        }
                      },
                      "required": [
                        "requestId",
                        "timestamp"
                      ]
                    }
                  },
                  "required": [
                    "data",
                    "meta"
                  ]
                }
              }
            }
          },
          "404": {
            "description": "No company configuration has been saved yet.",
            "content": {
              "application/json": {
                "schema": {
                  "type": "object",
                  "properties": {
                    "errors": {
                      "type": "array",
                      "items": {
                        "type": "object",
                        "properties": {
                          "code": {
                            "type": "string"
                          },
                          "message": {
                            "type": "string"
                          }
                        },
                        "required": [
                          "code",
                          "message"
                        ]
                      }
                    },
                    "meta": {
                      "type": "object",
                      "properties": {
                        "requestId": {
                          "type": "string"
                        },
                        "timestamp": {
                          "type": "string",
                          "format": "date-time"
                        }
                      },
                      "required": [
                        "requestId",
                        "timestamp"
                      ]
                    }
                  },
                  "required": [
                    "errors",
                    "meta"
                  ],
                  "description": "No company configuration has been saved yet."
                }
              }
            }
          }
        }
      }
    },
    "/api/invoices": {
      "get": {
        "summary": "List all invoices",
        "tags": [
          "Invoices"
        ],
        "description": "Returns a summary list of all invoices stored in the system, ordered by creation time. The XML body is omitted from list responses for performance.",
        "responses": {
          "200": {
            "description": "Default Response",
            "content": {
              "application/json": {
                "schema": {
                  "type": "object",
                  "properties": {
                    "data": {
                      "type": "array",
                      "items": {
                        "type": "object",
                        "properties": {
                          "id": {
                            "type": "string",
                            "format": "uuid",
                            "description": "Unique invoice identifier."
                          },
                          "orderId": {
                            "type": "string",
                            "description": "Identifier of the originating sale order."
                          },
                          "accessCode": {
                            "type": "string",
                            "description": "49-digit SRI access code that uniquely identifies the voucher. Includes emission date, voucher type, RUC, environment, sequence, and a mod-11 check digit.",
                            "example": "2412202401179214100100120010010000000011234567811"
                          },
                          "status": {
                            "type": "string",
                            "description": "Current lifecycle status of the invoice.",
                            "enum": [
                              "CREATED",
                              "SIGNED",
                              "SENT",
                              "AUTHORIZED",
                              "REJECTED"
                            ],
                            "example": "AUTHORIZED"
                          },
                          "signatureId": {
                            "type": "string",
                            "format": "uuid",
                            "description": "ID of the digital certificate used to sign the invoice XML."
                          },
                          "statusHistory": {
                            "type": "array",
                            "description": "Ordered list of all status transitions the invoice has gone through.",
                            "items": {
                              "type": "object",
                              "description": "A single status transition recorded on the invoice audit trail.",
                              "properties": {
                                "name": {
                                  "type": "string",
                                  "description": "Status name at the time of the transition.",
                                  "example": "SIGNED"
                                },
                                "statusDate": {
                                  "type": "string",
                                  "format": "date-time",
                                  "description": "ISO 8601 timestamp when the transition occurred."
                                },
                                "description": {
                                  "type": "string",
                                  "description": "Optional message from SRI or internal notes attached to the transition."
                                }
                              }
                            }
                          }
                        }
                      }
                    },
                    "meta": {
                      "type": "object",
                      "properties": {
                        "requestId": {
                          "type": "string"
                        },
                        "timestamp": {
                          "type": "string",
                          "format": "date-time"
                        }
                      },
                      "required": [
                        "requestId",
                        "timestamp"
                      ]
                    }
                  },
                  "required": [
                    "data",
                    "meta"
                  ]
                }
              }
            }
          }
        }
      }
    },
    "/api/invoices/{id}": {
      "get": {
        "summary": "Get an invoice by ID",
        "tags": [
          "Invoices"
        ],
        "description": "Returns full invoice detail including the signed XML and complete status history.",
        "parameters": [
          {
            "schema": {
              "type": "string",
              "format": "uuid"
            },
            "in": "path",
            "name": "id",
            "required": true,
            "description": "Invoice UUID."
          }
        ],
        "responses": {
          "200": {
            "description": "Default Response",
            "content": {
              "application/json": {
                "schema": {
                  "type": "object",
                  "properties": {
                    "data": {
                      "type": "object",
                      "properties": {
                        "id": {
                          "type": "string",
                          "format": "uuid",
                          "description": "Unique invoice identifier."
                        },
                        "orderId": {
                          "type": "string",
                          "description": "Identifier of the originating sale order."
                        },
                        "accessCode": {
                          "type": "string",
                          "description": "49-digit SRI access code that uniquely identifies the voucher. Includes emission date, voucher type, RUC, environment, sequence, and a mod-11 check digit.",
                          "example": "2412202401179214100100120010010000000011234567811"
                        },
                        "status": {
                          "type": "string",
                          "description": "Current lifecycle status of the invoice.",
                          "enum": [
                            "CREATED",
                            "SIGNED",
                            "SENT",
                            "AUTHORIZED",
                            "REJECTED"
                          ],
                          "example": "AUTHORIZED"
                        },
                        "signatureId": {
                          "type": "string",
                          "format": "uuid",
                          "description": "ID of the digital certificate used to sign the invoice XML."
                        },
                        "statusHistory": {
                          "type": "array",
                          "description": "Ordered list of all status transitions the invoice has gone through.",
                          "items": {
                            "type": "object",
                            "description": "A single status transition recorded on the invoice audit trail.",
                            "properties": {
                              "name": {
                                "type": "string",
                                "description": "Status name at the time of the transition.",
                                "example": "SIGNED"
                              },
                              "statusDate": {
                                "type": "string",
                                "format": "date-time",
                                "description": "ISO 8601 timestamp when the transition occurred."
                              },
                              "description": {
                                "type": "string",
                                "description": "Optional message from SRI or internal notes attached to the transition."
                              }
                            }
                          }
                        },
                        "xml": {
                          "type": "string",
                          "description": "Full signed invoice XML in SRI format. Present only in the detail endpoint."
                        }
                      }
                    },
                    "meta": {
                      "type": "object",
                      "properties": {
                        "requestId": {
                          "type": "string"
                        },
                        "timestamp": {
                          "type": "string",
                          "format": "date-time"
                        }
                      },
                      "required": [
                        "requestId",
                        "timestamp"
                      ]
                    }
                  },
                  "required": [
                    "data",
                    "meta"
                  ]
                }
              }
            }
          },
          "404": {
            "description": "No invoice found with the given ID.",
            "content": {
              "application/json": {
                "schema": {
                  "type": "object",
                  "properties": {
                    "errors": {
                      "type": "array",
                      "items": {
                        "type": "object",
                        "properties": {
                          "code": {
                            "type": "string"
                          },
                          "message": {
                            "type": "string"
                          }
                        },
                        "required": [
                          "code",
                          "message"
                        ]
                      }
                    },
                    "meta": {
                      "type": "object",
                      "properties": {
                        "requestId": {
                          "type": "string"
                        },
                        "timestamp": {
                          "type": "string",
                          "format": "date-time"
                        }
                      },
                      "required": [
                        "requestId",
                        "timestamp"
                      ]
                    }
                  },
                  "required": [
                    "errors",
                    "meta"
                  ],
                  "description": "No invoice found with the given ID."
                }
              }
            }
          }
        }
      }
    }
  }
}